simre/__init__.py
simre/formats.py
simre/init_models.py
simre/similarity.py
simre-0.0.3.dist-info/LICENSE
simre-0.0.3.dist-info/METADATA
simre-0.0.3.dist-info/WHEEL
simre-0.0.3.dist-info/top_level.txt
simre-0.0.3.dist-info/RECORD
