Metadata-Version: 2.1
Name: simre
Version: 0.0.3
Summary: Requirements Similarity tool for Software Product Lines
Author-email: María Isabel Limaylla <mlimaylla@udc.es>
Project-URL: Homepage, https://github.com/lbdudc/simre
Project-URL: Issues, https://github.com/lbdudc/simre/issues
Keywords: Software Product Lines,Similar Requirements
Classifier: Programming Language :: Python :: 3
Classifier: License :: OSI Approved :: MIT License
Classifier: Operating System :: OS Independent
Requires-Python: >=3.8
License-File: LICENSE
Requires-Dist: nltk
Requires-Dist: pandas
Requires-Dist: numpy
Requires-Dist: gensim
Requires-Dist: spacy
Requires-Dist: torch
Requires-Dist: sentence-transformers
Requires-Dist: bs4
Requires-Dist: uvlparser ==2.0.1
Requires-Dist: lxml
Requires-Dist: scikit-learn
Requires-Dist: fasttext-wheel
Requires-Dist: gdown
